{
  "slug": "fud-faq-a-weekly-community-thread-week-67",
  "date": "2022-07-10",
  "translations": {
    "en": {
      "title": "FUD FAQ | A Weekly Community Thread | Week 67",
      "blocks": [
        {
          "type": "text",
          "tag": "h3",
          "value": "FUD FAQ | A Weekly Community Thread | Week 67"
        },
        {
          "type": "image",
          "src": "https://cdn-images-1.medium.com/max/800/0*pNRKjnLp0-bu7WCq.jpeg",
          "alt": "post image"
        },
        {
          "type": "text",
          "tag": "h3",
          "value": "Top Question of the Week"
        },
        {
          "type": "text",
          "tag": "li",
          "value": "What’s the next great wave in NFTs and web3?"
        },
        {
          "type": "text",
          "tag": "p",
          "value": "Instructible prints, apparel and renewables."
        },
        {
          "type": "text",
          "tag": "p",
          "value": "It’s all about the actual use of NFTs and web3 IRL and in the open metaverse."
        },
        {
          "type": "text",
          "tag": "p",
          "value": "This is why there is such a strong focus on continued build out, in this bear and beyond, of web3 mapping features, IRL production co-ops, flexible + rechargeable memberships, and everything that helps us bridge more people between inflation adjusted IRL activities and virtual means to seize the memes of production."
        },
        {
          "type": "text",
          "tag": "h3",
          "value": "Most Common Repeat Question"
        },
        {
          "type": "text",
          "tag": "li",
          "value": "Why does everything always start to look the same with all of these corporate web2 fashion clones of each other?"
        },
        {
          "type": "text",
          "tag": "p",
          "value": "Besides having no incentive and no imagination, let’s be real, their top goal is to “woo the kids” without being caught up in what horrible machine of perpetual surveillance, ad targeting and monoculture they’re wooing everyone into being trapped in dull grey amber within."
        },
        {
          "type": "text",
          "tag": "p",
          "value": "There’s something to be said about them simply choosing the least expensive, least effortful and most ubiquitous path as enterprise orientated software has eaten design. But that only holds true for as long as content monetisation remains closed."
        },
        {
          "type": "text",
          "tag": "p",
          "value": "Thankfully, everyone in the know in web3 is racing towards greater build out of truly open content monetisation methods for designers and creators of all kinds."
        },
        {
          "type": "image",
          "src": "https://cdn-images-1.medium.com/max/800/0*xNSHkHz8rICvpXPs",
          "alt": "post image"
        },
        {
          "type": "text",
          "tag": "h3",
          "value": "Top Controversies"
        },
        {
          "type": "text",
          "tag": "p",
          "value": "Is it really that much of a surprise that the self-proclaimed populariser responsible for utility entering the NFT conversation (And might as well have claimed to have invented the internet whilst at it) shilled the fuck out of The Saudis drop and dumped directly back on his followers within hours."
        },
        {
          "type": "text",
          "tag": "p",
          "value": "If you’ve been in NFTs longer than a few minutes, or February 2021, then no surprise at all."
        },
        {
          "type": "image",
          "src": "https://cdn-images-1.medium.com/max/800/1*cAJWW4u0VTyZq5RAeDyULg.png",
          "alt": "post image"
        },
        {
          "type": "text",
          "tag": "h3",
          "value": "Silly Fails and Trolling"
        },
        {
          "type": "text",
          "tag": "p",
          "value": "Was it one huge troll all along to distract from everything else going wrong? At this stage, it seems more plausible than pulling out because of bots. But, here’s hoping for the best so crypto twitter remains a great place to be until all of web2 social media is soon replaced by true web3 so we never have to hear another word about web5 or Elon’s latest kids again 🤣"
        },
        {
          "type": "text",
          "tag": "h3",
          "value": "View all FUD FAQ here."
        },
        {
          "type": "text",
          "tag": "h3",
          "value": "If you would like a question answered or contribute content to next weeks article please reach out through our DIGITALAX Discord server in #FUD-FAQ channel!"
        },
        {
          "type": "text",
          "tag": "h3",
          "value": "Join our Community!"
        },
        {
          "type": "text",
          "tag": "li",
          "value": "Twitter: https://twitter.com/DIGITALAX_"
        },
        {
          "type": "text",
          "tag": "li",
          "value": "Discord: https://discord.gg/DKbSqRGtKv"
        },
        {
          "type": "text",
          "tag": "li",
          "value": "Medium: https://medium.com/@digitalax"
        },
        {
          "type": "text",
          "tag": "li",
          "value": "Telegram: https://t.me/digitalaxTG"
        },
        {
          "type": "text",
          "tag": "li",
          "value": "Github: https://github.com/DIGITALAX/"
        },
        {
          "type": "text",
          "tag": "li",
          "value": "Instagram: https://www.instagram.com/_digitalax /"
        }
      ]
    },
    "es": {
      "title": "FUD FAQ | Un hilo comunitario semanal | semana 67",
      "blocks": [
        {
          "type": "text",
          "tag": "h3",
          "value": "FUD FAQ | Un hilo comunitario semanal | semana 67"
        },
        {
          "type": "image",
          "src": "https://cdn-images-1.medium.com/max/800/0*pNRKjnLp0-bu7WCq.jpeg",
          "alt": "imagen de publicacion"
        },
        {
          "type": "text",
          "tag": "h3",
          "value": "Top pregunta de el semana"
        },
        {
          "type": "text",
          "tag": "li",
          "value": "What’s el next great wave en NFTs y web3?"
        },
        {
          "type": "text",
          "tag": "p",
          "value": "Instructible prints, apparel y renewables."
        },
        {
          "type": "text",
          "tag": "p",
          "value": "It’s all about el actual use de NFTs y web3 IRL y en el open metaverse."
        },
        {
          "type": "text",
          "tag": "p",
          "value": "This is por que there is such a strong focus en continued build out, en this bear y beyond, de web3 mapping features, IRL production co-ops, flexible + rechargeable memberships, y everything that helps us bridge more people between inflation adjusted IRL activities y virtual means a seize el memes de production."
        },
        {
          "type": "text",
          "tag": "h3",
          "value": "Most Common Repeat pregunta"
        },
        {
          "type": "text",
          "tag": "li",
          "value": "por que does everything always start a look el same con all de these corporate web2 moda clones de each other?"
        },
        {
          "type": "text",
          "tag": "p",
          "value": "Besides having no incentive y no imagination, let’s be real, their top goal is a “woo el kids” without being caught up en what horrible machine de perpetual surveillance, ad targeting y monoculture they’re wooing everyone into being trapped en dull grey amber within."
        },
        {
          "type": "text",
          "tag": "p",
          "value": "There’s something a be said about them simply choosing el least expensive, least effortful y most ubiquitous path as enterprise orientated software has eaten design. But that only holds true para as long as content monetisation remains closed."
        },
        {
          "type": "text",
          "tag": "p",
          "value": "Thankfully, everyone en el know en web3 is racing towards greater build out de truly open content monetisation methods para designers y creators de all kinds."
        },
        {
          "type": "image",
          "src": "https://cdn-images-1.medium.com/max/800/0*xNSHkHz8rICvpXPs",
          "alt": "imagen de publicacion"
        },
        {
          "type": "text",
          "tag": "h3",
          "value": "Principales controversias"
        },
        {
          "type": "text",
          "tag": "p",
          "value": "Is it really that much de a surprise that el self-proclaimed populariser responsible para utility entering el NFT conversation (y might as well have claimed a have invented el internet whilst at it) shilled el fuck out de el Saudis drop y dumped directly back en his followers within hours."
        },
        {
          "type": "text",
          "tag": "p",
          "value": "If you’ve been en NFTs longer than a few minutes, or February 2021, then no surprise at all."
        },
        {
          "type": "image",
          "src": "https://cdn-images-1.medium.com/max/800/1*cAJWW4u0VTyZq5RAeDyULg.png",
          "alt": "imagen de publicacion"
        },
        {
          "type": "text",
          "tag": "h3",
          "value": "Silly Fails y Trolling"
        },
        {
          "type": "text",
          "tag": "p",
          "value": "Was it one huge troll all along a distract de everything else going wrong? At this stage, it seems more plausible than pulling out because de bots. But, here’s hoping para el best so crypto twitter remains a great place a be until all de web2 social media is soon replaced by true web3 so we never have a hear another word about web5 or Elon’s latest kids again 🤣"
        },
        {
          "type": "text",
          "tag": "h3",
          "value": "Mira todo el FUD FAQ aquí."
        },
        {
          "type": "text",
          "tag": "h3",
          "value": "If you would like a pregunta answered or contribute content a next weeks article please reach out through our DIGITALAX Discord server en #FUD-FAQ channel!"
        },
        {
          "type": "text",
          "tag": "h3",
          "value": "Unete a nuestra comunidad!"
        },
        {
          "type": "text",
          "tag": "li",
          "value": "X (Twitter): https://twitter.com/DIGITALAX_"
        },
        {
          "type": "text",
          "tag": "li",
          "value": "Discord (comunidad): https://discord.gg/DKbSqRGtKv"
        },
        {
          "type": "text",
          "tag": "li",
          "value": "Medium (blog): https://medium.com/@digitalax"
        },
        {
          "type": "text",
          "tag": "li",
          "value": "Telegram (canal): https://t.me/digitalaxTG"
        },
        {
          "type": "text",
          "tag": "li",
          "value": "GitHub: https://github.com/DIGITALAX/"
        },
        {
          "type": "text",
          "tag": "li",
          "value": "Instagram: https://www.instagram.com/_digitalax /"
        }
      ]
    },
    "ar": {
      "title": "FUD FAQ | ثريد مجتمعي اسبوعي | اسبوع 67",
      "blocks": [
        {
          "type": "text",
          "tag": "h3",
          "value": "FUD FAQ | ثريد مجتمعي اسبوعي | اسبوع 67"
        },
        {
          "type": "image",
          "src": "https://cdn-images-1.medium.com/max/800/0*pNRKjnLp0-bu7WCq.jpeg",
          "alt": "صورة بوست"
        },
        {
          "type": "text",
          "tag": "h3",
          "value": "Top سؤال من ال اسبوع"
        },
        {
          "type": "text",
          "tag": "li",
          "value": "What’s ال next great wave في NFTs و web3?"
        },
        {
          "type": "text",
          "tag": "p",
          "value": "Instructible prints, apparel و renewables."
        },
        {
          "type": "text",
          "tag": "p",
          "value": "It’s all about ال actual use من NFTs و web3 IRL و في ال open metaverse."
        },
        {
          "type": "text",
          "tag": "p",
          "value": "This is ليه there is such a strong focus على continued build out, في this bear و beyond, من web3 mapping features, IRL production co-ops, flexible + rechargeable memberships, و everything that helps us bridge more people between inflation adjusted IRL activities و virtual means الى seize ال memes من production."
        },
        {
          "type": "text",
          "tag": "h3",
          "value": "Most Common Repeat سؤال"
        },
        {
          "type": "text",
          "tag": "li",
          "value": "ليه does everything always start الى look ال same مع all من these corporate web2 فاشون clones من each other?"
        },
        {
          "type": "text",
          "tag": "p",
          "value": "Besides having no incentive و no imagination, let’s be real, their top goal is الى “woo ال kids” without being caught up في what horrible machine من perpetual surveillance, ad targeting و monoculture they’re wooing everyone into being trapped في dull grey amber within."
        },
        {
          "type": "text",
          "tag": "p",
          "value": "There’s something الى be said about them simply choosing ال least expensive, least effortful و most ubiquitous path as enterprise orientated software has eaten design. But that only holds true لـ as long as content monetisation remains closed."
        },
        {
          "type": "text",
          "tag": "p",
          "value": "Thankfully, everyone في ال know في web3 is racing towards greater build out من truly open content monetisation methods لـ designers و creators من all kinds."
        },
        {
          "type": "image",
          "src": "https://cdn-images-1.medium.com/max/800/0*xNSHkHz8rICvpXPs",
          "alt": "صورة بوست"
        },
        {
          "type": "text",
          "tag": "h3",
          "value": "أهم الجدل"
        },
        {
          "type": "text",
          "tag": "p",
          "value": "Is it really that much من a surprise that ال self-proclaimed populariser responsible لـ utility entering ال NFT conversation (و might as well have claimed الى have invented ال internet whilst at it) shilled ال fuck out من ال Saudis drop و dumped directly back على his followers within hours."
        },
        {
          "type": "text",
          "tag": "p",
          "value": "If you’ve been في NFTs longer than a few minutes, or February 2021, then no surprise at all."
        },
        {
          "type": "image",
          "src": "https://cdn-images-1.medium.com/max/800/1*cAJWW4u0VTyZq5RAeDyULg.png",
          "alt": "صورة بوست"
        },
        {
          "type": "text",
          "tag": "h3",
          "value": "Silly Fails و Trolling"
        },
        {
          "type": "text",
          "tag": "p",
          "value": "Was it one huge troll all along الى distract من everything else going wrong? At this stage, it seems more plausible than pulling out because من bots. But, here’s hoping لـ ال best so crypto twitter remains a great place الى be until all من web2 سوشيال media is soon replaced by true web3 so we never have الى hear another word about web5 or Elon’s latest kids again 🤣"
        },
        {
          "type": "text",
          "tag": "h3",
          "value": "شوف كل FUD FAQ من هنا."
        },
        {
          "type": "text",
          "tag": "h3",
          "value": "If you would like a سؤال answered or contribute content الى next weeks article please reach out through our DIGITALAX Discord server في #FUD-FAQ channel!"
        },
        {
          "type": "text",
          "tag": "h3",
          "value": "انضم لمجتمعنا!"
        },
        {
          "type": "text",
          "tag": "li",
          "value": "إكس (تويتر): https://twitter.com/DIGITALAX_"
        },
        {
          "type": "text",
          "tag": "li",
          "value": "ديسكورد: https://discord.gg/DKbSqRGtKv"
        },
        {
          "type": "text",
          "tag": "li",
          "value": "ميديوم: https://medium.com/@digitalax"
        },
        {
          "type": "text",
          "tag": "li",
          "value": "تيليجرام: https://t.me/digitalaxTG"
        },
        {
          "type": "text",
          "tag": "li",
          "value": "جيت هاب: https://github.com/DIGITALAX/"
        },
        {
          "type": "text",
          "tag": "li",
          "value": "إنستجرام: https://www.instagram.com/_digitalax /"
        }
      ]
    }
  }
}
